ffmpegarm64v8a_mkkk/__init__.py
ffmpegarm64v8a_mkkk/ffmpeg..bin
ffmpegarm64v8a_mkkk/ffmpeg.so
ffmpegarm64v8a_mkkk/libffmpeg.so
ffmpegarm64v8a_mkkk/module1.py
ffmpegarm64v8a_mkkk-0.3.0.dist-info/License
ffmpegarm64v8a_mkkk-0.3.0.dist-info/METADATA
ffmpegarm64v8a_mkkk-0.3.0.dist-info/WHEEL
ffmpegarm64v8a_mkkk-0.3.0.dist-info/top_level.txt
ffmpegarm64v8a_mkkk-0.3.0.dist-info/RECORD
